README.md
setup.py
k50_tracker/__init__.py
k50_tracker/client.py
k50_tracker/exceptions.py
k50_tracker/helpers.py
k50_tracker_api.egg-info/PKG-INFO
k50_tracker_api.egg-info/SOURCES.txt
k50_tracker_api.egg-info/dependency_links.txt
k50_tracker_api.egg-info/requires.txt
k50_tracker_api.egg-info/top_level.txt