Metadata-Version: 2.1
Name: k50-tracker-api
Version: 0.0.3
Summary: K50 tracker api wrapper
Home-page: https://github.com/bzdvdn/k50-tracker-api
Author: bzdvdn
Author-email: bzdv.dn@gmail.com
License: MIT
Platform: UNKNOWN
Requires-Python: >=3.6
